{
  "Customers": [
    {
      "Name": "Aniket",
      "Shares": 219,
      "Amount": 44740,
      "TrasactionDate": "2019-05-25T05:39:05.209Z"
    },
    {
      "Name": "Shubham",
      "Shares": 1500,
      "Amount": 111000,
      "TrasactionDate": "2019-05-23T05:59:12.365Z"
    },
    {
      "Name": "Dhoni",
      "Shares": 500,
      "Amount": 2500000,
      "TrasactionDate": ""
    },
    {
      "Name": "Arti",
      "Shares": 200,
      "Amount": 25000,
      "TrasactionDate": ""
    },
    {
      "Name": "Shrikant",
      "Shares": 50,
      "Amount": 2326,
      "TrasactionDate": ""
    },
    {
      "Name": "Ashwini",
      "Shares": 54,
      "Amount": 12122,
      "TrasactionDate": ""
    },
    {
      "Name": "Demo",
      "Shares": 54,
      "Amount": 45454,
      "TrasactionDate": ""
    }
  ],
  "CompanyShare": [
    {
      "CName": "IBM",
      "CSymbol": "IBM",
      "Shares": 1000,
      "Amount": 105060
    },
    {
      "CName": "Congnizant",
      "CSymbol": "C",
      "Shares": 1381,
      "Amount": 106160
    },
    {
      "CName": "Infosys",
      "CSymbol": "I",
      "Shares": 15000,
      "Amount": 100000
    },
    {
      "CName": "TCS",
      "CSymbol": "TCS",
      "Shares": 5000,
      "Amount": 100000
    },
    {
      "CName": "ThoughWorks",
      "CSymbol": "TW",
      "Shares": 22500,
      "Amount": 100000
    },
    {
      "CName": "HCL",
      "CSymbol": "HCL",
      "Shares": 54,
      "Amount": 12121
    },
    {
      "CName": "BridgeLabz",
      "CSymbol": "B",
      "Shares": 54,
      "Amount": 142121
    }
  ],
  "TransactionHistory": [
    {
      "Sold": "Company Symbol : C Trasaction done sold to the customer : Sat May 25 2019 11:05:56 GMT+0530 (IST)"
    },
    {
      "Sold": "Company Symbol : C Trasaction done sold to the customer : Sat May 25 2019 11:08:37 GMT+0530 (IST)"
    },
    {
      "Buy": "Company Symbol : C Trasaction done Buy to the customer : Sat May 25 2019 11:09:05 GMT+0530 (IST)"
    }
  ]
}